Metadata-Version: 2.1
Name: batch-tar
Version: 0.1
Summary: To tar/compress files/directories in batch mode.
Home-page: https://github.com/linzhi2013/batch_tar
Author: Guanliang Meng
Author-email: linzhi2012@gmail.com
License: UNKNOWN
Platform: UNKNOWN
Classifier: Development Status :: 3 - Alpha
Classifier: Intended Audience :: Science/Research
Classifier: Topic :: Utilities
Classifier: License :: OSI Approved :: GNU General Public License v3 or later (GPLv3+)
Classifier: Programming Language :: Python :: 3
Classifier: Operating System :: MacOS :: MacOS X
Classifier: Operating System :: POSIX :: Linux
Requires-Python: >=3
